{"v":3,"stories":{"angularcomponent--primary":{"id":"angularcomponent--primary","name":"Primary","title":"AngularComponent","importPath":"./libs/angular/src/lib/angular/angular.component.stories.ts","tags":["story"],"kind":"AngularComponent","story":"Primary","parameters":{"__id":"angularcomponent--primary","docsOnly":false,"fileName":"./libs/angular/src/lib/angular/angular.component.stories.ts"}},"angularcomponent--heading":{"id":"angularcomponent--heading","name":"Heading","title":"AngularComponent","importPath":"./libs/angular/src/lib/angular/angular.component.stories.ts","tags":["play-fn","story"],"kind":"AngularComponent","story":"Heading","parameters":{"__id":"angularcomponent--heading","docsOnly":false,"fileName":"./libs/angular/src/lib/angular/angular.component.stories.ts"}}}}
